ai/backend/console/__init__.py
ai/backend/console/auth.py
ai/backend/console/logging.py
ai/backend/console/proxy.py
ai/backend/console/server.py
ai/backend/console/static/.git
ai/backend/console/static/README.md
ai/backend/console/static/config.toml
ai/backend/console/static/default.toml
ai/backend/console/static/index.html
ai/backend/console/static/manifest.json
ai/backend/console/static/sw.js
ai/backend/console/static/sw.js.map
ai/backend/console/static/version.json
ai/backend/console/static/workbox-4681948c.js
ai/backend/console/static/workbox-4681948c.js.map
ai/backend/console/static/dist/components/backend-ai-agent-view-7fd2648b.js
ai/backend/console/static/dist/components/backend-ai-change-forgot-password-view-b84bb0dc.js
ai/backend/console/static/dist/components/backend-ai-chart-9b4f931f.js
ai/backend/console/static/dist/components/backend-ai-console-64041d0c.js
ai/backend/console/static/dist/components/backend-ai-console.js
ai/backend/console/static/dist/components/backend-ai-credential-view-40195922.js
ai/backend/console/static/dist/components/backend-ai-data-view-43697489.js
ai/backend/console/static/dist/components/backend-ai-email-verification-view-98ab1c36.js
ai/backend/console/static/dist/components/backend-ai-environment-view-27c6510d.js
ai/backend/console/static/dist/components/backend-ai-error-view-59ac9078.js
ai/backend/console/static/dist/components/backend-ai-import-view-18a95005.js
ai/backend/console/static/dist/components/backend-ai-information-view-8398d2e8.js
ai/backend/console/static/dist/components/backend-ai-maintenance-view-67783404.js
ai/backend/console/static/dist/components/backend-ai-permission-denied-view-2a4a9c2c.js
ai/backend/console/static/dist/components/backend-ai-session-launcher-04c6cab9.js
ai/backend/console/static/dist/components/backend-ai-session-view-7721506e.js
ai/backend/console/static/dist/components/backend-ai-settings-view-1ce9d881.js
ai/backend/console/static/dist/components/backend-ai-statistics-view-ab36390f.js
backend.ai_console_server-20.9.7.dist-info/METADATA
backend.ai_console_server-20.9.7.dist-info/WHEEL
backend.ai_console_server-20.9.7.dist-info/top_level.txt
backend.ai_console_server-20.9.7.dist-info/RECORD
