Metadata-Version: 2.1
Name: backend.ai-console-server
Version: 20.9.7
Summary: Backend.AI Console Server
Home-page: https://backend.ai
Author: Lablup Inc.
Author-email: devops@lablup.com
License: Proprietary
Project-URL: Documentation, https://docs.backend.ai
Platform: UNKNOWN
Classifier: Intended Audience :: Developers
Classifier: Programming Language :: Python
Classifier: Programming Language :: Python :: 3
Classifier: Operating System :: POSIX
Classifier: Operating System :: MacOS :: MacOS X
Classifier: Environment :: No Input/Output (Daemon)
Classifier: Topic :: Scientific/Engineering
Classifier: Topic :: Software Development
Requires-Python: >=3.7
Requires-Dist: aiohttp (~=3.7.3)
Requires-Dist: aiohttp-cors (~=0.7)
Requires-Dist: aiohttp-session[aioredis] (~=2.9.0)
Requires-Dist: aioredis (~=1.3.1)
Requires-Dist: aiotools (~=1.2.1)
Requires-Dist: async-timeout (~=3.0)
Requires-Dist: attrs (>=20.2)
Requires-Dist: click (>=7.1)
Requires-Dist: coloredlogs (>=10.0)
Requires-Dist: jinja2 (~=2.11.2)
Requires-Dist: uvloop (~=0.14.0)
Requires-Dist: setproctitle (>=1.2.1)
Requires-Dist: toml (>=0.10.0)
Requires-Dist: backend.ai-client (>=20.9.0)
Provides-Extra: build
Requires-Dist: wheel (>=0.33.6) ; extra == 'build'
Requires-Dist: twine (>=1.14.0) ; extra == 'build'
Requires-Dist: towncrier (~=19.2.0) ; extra == 'build'
Provides-Extra: dev
Requires-Dist: pytest-sugar (>=0.9.2) ; extra == 'dev'
Provides-Extra: lint
Requires-Dist: flake8 (~=3.8.4) ; extra == 'lint'
Provides-Extra: test
Requires-Dist: pytest (~=6.1.1) ; extra == 'test'
Requires-Dist: pytest-asyncio (~=0.14.0) ; extra == 'test'
Requires-Dist: pytest-aiohttp (~=0.3.0) ; extra == 'test'
Requires-Dist: pytest-cov ; extra == 'test'
Requires-Dist: pytest-mock (~=3.3.1) ; extra == 'test'
Requires-Dist: codecov ; extra == 'test'
Provides-Extra: typecheck
Requires-Dist: mypy (>=0.790) ; extra == 'typecheck'
